gas_network_sdk/__init__.py
gas_network_sdk/client.py
gas_network_sdk/exceptions.py
gas_network_sdk/types.py
gas_network_sdk-0.1.0.dist-info/licenses/LICENSE
gas_network_sdk-0.1.0.dist-info/METADATA
gas_network_sdk-0.1.0.dist-info/WHEEL
gas_network_sdk-0.1.0.dist-info/top_level.txt
gas_network_sdk-0.1.0.dist-info/RECORD
