Metadata-Version: 2.4
Name: gas-network-sdk
Version: 0.1.0
Summary: Python SDK for Gas Network API - gas price prediction and optimization
Author: rshuwy
Project-URL: Homepage, https://github.com/rshuwy/gas-network-python-sdk
Project-URL: Bug Tracker, https://github.com/rshuwy/gas-network-python-sdk/issues
Project-URL: Repository, https://github.com/rshuwy/gas-network-python-sdk
Project-URL: Documentation, https://github.com/rshuwy/gas-network-python-sdk#readme
Keywords: gas,ethereum,blockchain,web3,api,gas-prices
Classifier: Development Status :: 4 - Beta
Classifier: Intended Audience :: Developers
Classifier: License :: OSI Approved :: MIT License
Classifier: Operating System :: OS Independent
Classifier: Programming Language :: Python :: 3
Classifier: Programming Language :: Python :: 3.8
Classifier: Programming Language :: Python :: 3.9
Classifier: Programming Language :: Python :: 3.10
Classifier: Programming Language :: Python :: 3.11
Classifier: Programming Language :: Python :: 3.12
Classifier: Topic :: Software Development :: Libraries :: Python Modules
Classifier: Topic :: Internet :: WWW/HTTP :: Dynamic Content
Classifier: Topic :: Office/Business :: Financial
Requires-Python: >=3.8
License-File: LICENSE
Requires-Dist: httpx>=0.24.0
Requires-Dist: pydantic>=2.0.0
Provides-Extra: dev
Requires-Dist: pytest>=7.0.0; extra == "dev"
Requires-Dist: pytest-asyncio>=0.21.0; extra == "dev"
Requires-Dist: pytest-httpx>=0.21.0; extra == "dev"
Requires-Dist: black>=23.0.0; extra == "dev"
Requires-Dist: mypy>=1.0.0; extra == "dev"
Requires-Dist: ruff>=0.1.0; extra == "dev"
Dynamic: license-file
